src/__init__.py
src/generic.py
memnoch_utils_generic-0.1.1.dist-info/LICENSE
memnoch_utils_generic-0.1.1.dist-info/METADATA
memnoch_utils_generic-0.1.1.dist-info/WHEEL
memnoch_utils_generic-0.1.1.dist-info/top_level.txt
memnoch_utils_generic-0.1.1.dist-info/RECORD
