Metadata-Version: 2.1
Name: memnoch-utils-generic
Version: 0.1.1
Summary: UNKNOWN
Home-page: https://github.com/Memnoch9178/mem-utils
Author: Guillaume LEFEBVRE
Author-email: guillaume@ldmail.fr
License: UNKNOWN
Platform: UNKNOWN
Classifier: Programming Language :: Python :: 3
Classifier: License :: OSI Approved :: MIT License
Classifier: Operating System :: OS Independent
Requires-Python: >=3.6
License-File: LICENSE
Requires-Dist: memnoch-utils-generic-literal
